openai_async/__init__.py
openai_async/openai_async.py
openai_async/test_openai_async.py
openai_async/test_utils.py
openai_async-0.0.3.dist-info/LICENCE
openai_async-0.0.3.dist-info/METADATA
openai_async-0.0.3.dist-info/WHEEL
openai_async-0.0.3.dist-info/top_level.txt
openai_async-0.0.3.dist-info/RECORD
