Metadata-Version: 2.1
Name: openai-async
Version: 0.0.3
Summary: A light-weight, asynchronous client for OpenAI API - text completion, image generation and embeddings.
Home-page: https://github.com/itayzit/openai-async
Author: itayzit
Author-email: itayzit@gmail.com
License: MIT
Platform: UNKNOWN
License-File: LICENCE
